api/config.py
api/console_stringifier.py
api/export.py
api/parsers.py
api/printable_result.py
api/res.py
application/cache.py
application/helpers.py
application/latex_ifelse.py
application/latex_stringifier.py
application/rounder.py
application/stringifier.py
domain/result.py
domain/uncertainty.py
domain/value.py
resultwizard/__init__.py
resultwizard-0.1.dist-info/LICENSE
resultwizard-0.1.dist-info/METADATA
resultwizard-0.1.dist-info/WHEEL
resultwizard-0.1.dist-info/top_level.txt
resultwizard-0.1.dist-info/RECORD
