Metadata-Version: 2.1
Name: resultwizard
Version: 0.1
Summary: Intelligent interface between Python-computed values and your LaTeX work
Author: Paul Obernolte (paul019), Dominic Plein (Splines)
License: MIT License
Project-URL: Homepage, https://github.com/paul019/ResultWizard
Project-URL: Repository, https://github.com/paul019/ResultWizard
Project-URL: Issues, https://github.com/paul019/ResultWizard/issues
Project-URL: Changelog, https://github.com/paul019/ResultWizard/blob/main/CHANGELOG.md
Keywords: latex,variable,science,result,value,rounding,significant figures,jupyter
Classifier: Development Status :: 3 - Alpha
Classifier: Topic :: Scientific/Engineering :: Physics
Classifier: Topic :: Software Development :: Build Tools
Classifier: Topic :: Text Processing :: Markup :: LaTeX
Classifier: Intended Audience :: Science/Research
Classifier: License :: OSI Approved :: MIT License
Classifier: Programming Language :: Python :: 3.9
Classifier: Programming Language :: Python :: 3.10
Classifier: Programming Language :: Python :: 3.11
Classifier: Programming Language :: Python :: 3.12
Classifier: Programming Language :: Python :: 3.13
Requires-Python: >=3.8
License-File: LICENSE
Requires-Dist: plum-dispatch ~=2.3
